cli/__init__.py
cli/main.py
cli/templates/README.md.j2
cli/templates/agent.py.j2
cli/templates/agents_init.py.j2
cli/templates/common_models.py.j2
cli/templates/console.py.j2
cli/templates/env.j2
cli/templates/main.py.j2
cli/templates/requirements.txt.j2
cli/templates.py
cli/wizard.py
eggai/__init__.py
eggai/adapters/__init__.py
eggai/adapters/a2a/__init__.py
eggai/adapters/a2a/config.py
eggai/adapters/a2a/executor.py
eggai/adapters/a2a/plugin.py
eggai/adapters/mcp/__init__.py
eggai/adapters/mcp/mcp.py
eggai/adapters/mcp/models.py
eggai/agent.py
eggai/channel.py
eggai/hooks.py
eggai/schemas.py
eggai/transport/__init__.py
eggai/transport/base.py
eggai/transport/defaults.py
eggai/transport/inmemory.py
eggai/transport/kafka.py
eggai/transport/middleware_utils.py
eggai/transport/redis.py
eggai-0.2.9.dist-info/METADATA
eggai-0.2.9.dist-info/WHEEL
eggai-0.2.9.dist-info/entry_points.txt
eggai-0.2.9.dist-info/licenses/LICENSE
eggai-0.2.9.dist-info/RECORD
